Workbook

Sheet Region Summary
A1: Region Performance - Superstore (Task 18)
A3: Region | B3: Total Sales | C3: Total Profit | D3: Profit Margin (%) | E3: Rank by Sales | F3: Rank by Profit | G3: Rank by Margin
A4: Central | B4: =SUMIF(Data!$M:$M,A4,Data!$R:$R) | C4: =SUMIF(Data!$M:$M,A4,Data!$U:$U) | D4: =IF(B4=0,0,C4/B4*100) | E4: =RANK(B4,$B$4:$B$7) | F4: =RANK(C4,$C$4:$C$7) | G4: =RANK(D4,$D$4:$D$7)
A5: East | B5: =SUMIF(Data!$M:$M,A5,Data!$R:$R) | C5: =SUMIF(Data!$M:$M,A5,Data!$U:$U) | D5: =IF(B5=0,0,C5/B5*100) | E5: =RANK(B5,$B$4:$B$7) | F5: =RANK(C5,$C$4:$C$7) | G5: =RANK(D5,$D$4:$D$7)
A6: South | B6: =SUMIF(Data!$M:$M,A6,Data!$R:$R) | C6: =SUMIF(Data!$M:$M,A6,Data!$U:$U) | D6: =IF(B6=0,0,C6/B6*100) | E6: =RANK(B6,$B$4:$B$7) | F6: =RANK(C6,$C$4:$C$7) | G6: =RANK(D6,$D$4:$D$7)
A7: West | B7: =SUMIF(Data!$M:$M,A7,Data!$R:$R) | C7: =SUMIF(Data!$M:$M,A7,Data!$U:$U) | D7: =IF(B7=0,0,C7/B7*100) | E7: =RANK(B7,$B$4:$B$7) | F7: =RANK(C7,$C$4:$C$7) | G7: =RANK(D7,$D$4:$D$7)
A8: Total | B8: =SUM(B4:B7) | C8: =SUM(C4:C7) | D8: =IF(B8=0,0,C8/B8*100)

Sheet Data
A1: Row ID | B1: Order ID | C1: Order Date | D1: Ship Date | E1: Ship Mode | F1: Customer ID | G1: Customer Name | H1: Segment | I1: Country | J1: City | K1: State | L1: Postal Code | M1: Region | N1: Product ID | O1: Category | P1: Sub-Category | Q1: Product Name | R1: Sales | S1: Quantity | T1: Discount | U1: Profit | W1: <- Paste the Superstore data here from A2 (same column order: Region = M, Sales = R, Profit = U)
